invenio_drafts_resources/__init__.py
invenio_drafts_resources/auditlog/__init__.py
invenio_drafts_resources/auditlog/actions.py
invenio_drafts_resources/auditlog/context.py
invenio_drafts_resources/records/__init__.py
invenio_drafts_resources/records/api.py
invenio_drafts_resources/records/models.py
invenio_drafts_resources/records/systemfields/__init__.py
invenio_drafts_resources/records/systemfields/parent.py
invenio_drafts_resources/records/systemfields/versions.py
invenio_drafts_resources/resources/__init__.py
invenio_drafts_resources/resources/records/__init__.py
invenio_drafts_resources/resources/records/args.py
invenio_drafts_resources/resources/records/config.py
invenio_drafts_resources/resources/records/errors.py
invenio_drafts_resources/resources/records/resource.py
invenio_drafts_resources/services/__init__.py
invenio_drafts_resources/services/records/__init__.py
invenio_drafts_resources/services/records/config.py
invenio_drafts_resources/services/records/permissions.py
invenio_drafts_resources/services/records/schema.py
invenio_drafts_resources/services/records/search_params.py
invenio_drafts_resources/services/records/service.py
invenio_drafts_resources/services/records/tasks.py
invenio_drafts_resources/services/records/uow.py
invenio_drafts_resources/services/records/components/__init__.py
invenio_drafts_resources/services/records/components/base.py
invenio_drafts_resources/services/records/components/files.py
invenio_drafts_resources/services/records/components/media_files.py
invenio_drafts_resources/services/records/components/metadata.py
invenio_drafts_resources/services/records/components/pid.py
invenio_drafts_resources/services/records/components/relations.py
invenio_drafts_resources/translations/messages.pot
invenio_drafts_resources/translations/ar/LC_MESSAGES/messages.mo
invenio_drafts_resources/translations/ar/LC_MESSAGES/messages.po
invenio_drafts_resources/translations/bg/LC_MESSAGES/messages.mo
invenio_drafts_resources-8.0.0.dist-info/licenses/AUTHORS.rst
invenio_drafts_resources-8.0.0.dist-info/licenses/LICENSE
invenio_drafts_resources-8.0.0.dist-info/METADATA
invenio_drafts_resources-8.0.0.dist-info/WHEEL
invenio_drafts_resources-8.0.0.dist-info/entry_points.txt
invenio_drafts_resources-8.0.0.dist-info/top_level.txt
invenio_drafts_resources-8.0.0.dist-info/RECORD
